[
    {
        "Date": "2017-12-01",
        "bid_price": 99.916,
        "offer_price": 99.916375,
        "mid_price": 99.9161875,
        "eod_price": 99.926,
        "bid_yield": 1.1365102241438796,
        "offer_yield": 1.1314322713479965,
        "mid_yield": 1.133971247745938,
        "eod_yield": 1.0011111926529073
    },
    {
        "Date": "2017-12-04",
        "bid_price": 99.925333,
        "offer_price": 99.925667,
        "mid_price": 99.9255,
        "eod_price": 99.927806,
        "bid_yield": 1.1364091476183307,
        "offer_yield": 1.131321987239377,
        "mid_yield": 1.1338655674288538,
        "eod_yield": 1.0987436436527058
    },
    {
        "Date": "2017-12-05",
        "bid_price": 99.927167,
        "offer_price": 99.927486,
        "mid_price": 99.92732649999999,
        "eod_price": 99.930944,
        "bid_yield": 1.1566704812899435,
        "offer_yield": 1.1516007239228296,
        "mid_yield": 1.1541356026063867,
        "eod_yield": 1.096645995510887
    },
    {
        "Date": "2017-12-06",
        "bid_price": 99.930333,
        "offer_price": 99.930639,
        "mid_price": 99.930486,
        "eod_price": 99.9335,
        "bid_yield": 1.1566446632738516,
        "offer_yield": 1.151560779526844,
        "mid_yield": 1.1541027214003479,
        "eod_yield": 1.1040296342523133
    },
    {
        "Date": "2017-12-07",
        "bid_price": 99.934083,
        "offer_price": 99.934375,
        "mid_price": 99.934229,
        "eod_price": 99.936667,
        "bid_yield": 1.1464559474621072,
        "offer_yield": 1.1413740267049757,
        "mid_yield": 1.1439149870835414,
        "eod_yield": 1.1014854609298292
    },
    {
        "Date": "2017-12-08",
        "bid_price": 99.936111,
        "offer_price": 99.936389,
        "mid_price": 99.93625,
        "eod_price": 99.946167,
        "bid_yield": 1.166719655520774,
        "offer_yield": 1.1616396806171376,
        "mid_yield": 1.1641796680689558,
        "eod_yield": 0.9829814183869121
    },
    {
        "Date": "2017-12-11",
        "bid_price": 99.946167,
        "offer_price": 99.946403,
        "mid_price": 99.946285,
        "eod_price": 99.948889,
        "bid_yield": 1.156448727514014,
        "offer_yield": 1.1513762207600209,
        "mid_yield": 1.1539124741370175,
        "eod_yield": 1.0979444056594208
    },
    {
        "Date": "2017-12-12",
        "bid_price": 99.945778,
        "offer_price": 99.946,
        "mid_price": 99.945889,
        "eod_price": 99.949167,
        "bid_yield": 1.237610432128412,
        "offer_yield": 1.2325405719088773,
        "mid_yield": 1.2350755020186446,
        "eod_yield": 1.1602175859053803
    },
    {
        "Date": "2017-12-13",
        "bid_price": 99.94875,
        "offer_price": 99.948958,
        "mid_price": 99.94885400000001,
        "eod_price": 99.952556,
        "bid_yield": 1.2477227912637592,
        "offer_yield": 1.242656276616598,
        "mid_yield": 1.2451895339401786,
        "eod_yield": 1.1550186537167046
    },
    {
        "Date": "2017-12-14",
        "bid_price": 99.951778,
        "offer_price": 99.951972,
        "mid_price": 99.951875,
        "eod_price": 99.955583,
        "bid_yield": 1.2578229759667832,
        "offer_yield": 1.2527602471201151,
        "mid_yield": 1.2552916115434491,
        "eod_yield": 1.1585292267836915
    },
    {
        "Date": "2017-12-15",
        "bid_price": 99.955222,
        "offer_price": 99.955403,
        "mid_price": 99.9553125,
        "eod_price": 99.965,
        "bid_yield": 1.2577916754947394,
        "offer_yield": 1.2527052074027716,
        "mid_yield": 1.2552484414487555,
        "eod_yield": 0.9830363704218594
    },
    {
        "Date": "2017-12-18",
        "bid_price": 99.965,
        "offer_price": 99.965139,
        "mid_price": 99.9650695,
        "eod_price": 99.96825,
        "bid_yield": 1.2779472815484174,
        "offer_yield": 1.2728702352929617,
        "mid_yield": 1.2754087584206895,
        "eod_yield": 1.1592430596715328
    },
    {
        "Date": "2017-12-19",
        "bid_price": 99.9685,
        "offer_price": 99.968875,
        "mid_price": 99.9686875,
        "eod_price": 99.972222,
        "bid_yield": 1.2779025392996397,
        "offer_yield": 1.2626846772725877,
        "mid_yield": 1.2702936082861136,
        "eod_yield": 1.1268652428492942
    },
    {
        "Date": "2017-12-20",
        "bid_price": 99.972222,
        "offer_price": 99.972333,
        "mid_price": 99.9722775,
        "eod_price": 99.976083,
        "bid_yield": 1.2677233982054559,
        "offer_yield": 1.2626562140944746,
        "mid_yield": 1.2651898061499653,
        "eod_yield": 1.091474172877804
    },
    {
        "Date": "2017-12-21",
        "bid_price": 99.976472,
        "offer_price": 99.976667,
        "mid_price": 99.97656950000001,
        "eod_price": 99.98,
        "bid_yield": 1.2271058563229604,
        "offer_yield": 1.2169332327451603,
        "mid_yield": 1.2220195445340605,
        "eod_yield": 1.043065756008137
    },
    {
        "Date": "2017-12-22",
        "bid_price": 99.98,
        "offer_price": 0.0,
        "mid_price": 49.99,
        "eod_price": 99.993389,
        "bid_yield": 1.21691004867616,
        "offer_yield": null,
        "mid_yield": null,
        "eod_yield": 0.40219575582848505
    },
    {
        "Date": "2017-12-26",
        "bid_price": 99.993333,
        "offer_price": 0.0,
        "mid_price": 49.9966665,
        "eod_price": 99.996694,
        "bid_yield": 1.2168086246297438,
        "offer_yield": null,
        "mid_yield": null,
        "eod_yield": 0.6033649472442295
    },
    {
        "Date": "2017-12-29",
        "bid_price": 99.996611,
        "offer_price": 0.0,
        "mid_price": 49.9983055,
        "eod_price": 100.0,
        "bid_yield": null,
        "offer_yield": null,
        "mid_yield": null,
        "eod_yield": null
    }
]