[
    {
        "Date": "2024-02-01",
        "bid_price": 101.15625,
        "offer_price": 101.15625,
        "mid_price": 101.15625,
        "eod_price": 101.03125,
        "bid_yield": -0.14466216492652856,
        "offer_yield": -0.14466216492652856,
        "mid_yield": -0.14466216492652856,
        "eod_yield": -0.1248088843822475
    },
    {
        "Date": "2024-02-02",
        "bid_price": 99.875,
        "offer_price": 99.890625,
        "mid_price": 99.8828125,
        "eod_price": 99.90625,
        "bid_yield": 0.06010201575094749,
        "offer_yield": 0.05758677309306212,
        "mid_yield": 0.05884439442200481,
        "eod_yield": 0.055073907674742996
    },
    {
        "Date": "2024-02-05",
        "bid_price": 99.0625,
        "offer_price": 99.078125,
        "mid_price": 99.0703125,
        "eod_price": 99.0625,
        "bid_yield": 0.19142828154563937,
        "offer_yield": 0.18889201474189796,
        "mid_yield": 0.19016014814376866,
        "eod_yield": 0.19142828154563937
    },
    {
        "Date": "2024-02-06",
        "bid_price": 99.4375,
        "offer_price": 99.453125,
        "mid_price": 99.4453125,
        "eod_price": 99.59375,
        "bid_yield": 0.13067206788063085,
        "offer_yield": 0.1281462771892551,
        "mid_yield": 0.12940917253494297,
        "eod_yield": 0.10542987513542214
    },
    {
        "Date": "2024-02-07",
        "bid_price": 99.5625,
        "offer_price": 99.578125,
        "mid_price": 99.5703125,
        "eod_price": 99.46875,
        "bid_yield": 0.11047517085075415,
        "offer_yield": 0.10795252299308812,
        "mid_yield": 0.10921384692192113,
        "eod_yield": 0.12561981012403894
    },
    {
        "Date": "2024-02-08",
        "bid_price": 99.125,
        "offer_price": 99.125,
        "mid_price": 99.125,
        "eod_price": 99.09375,
        "bid_yield": 0.18128530955314673,
        "offer_yield": 0.18128530955314673,
        "mid_yield": 0.18128530955314673,
        "eod_yield": 0.18635574793815649
    },
    {
        "Date": "2024-02-09",
        "bid_price": 98.90625,
        "offer_price": 98.921875,
        "mid_price": 98.9140625,
        "eod_price": 98.96875,
        "bid_yield": 0.21681713986396825,
        "offer_yield": 0.21427668261528054,
        "mid_yield": 0.21554691123962438,
        "eod_yield": 0.2066563584804539
    },
    {
        "Date": "2024-02-12",
        "bid_price": 98.9375,
        "offer_price": 98.9375,
        "mid_price": 98.9375,
        "eod_price": 99.03125,
        "bid_yield": 0.21173622536659276,
        "offer_yield": 0.21173622536659276,
        "mid_yield": 0.21173622536659276,
        "eod_yield": 0.1965029103755954
    },
    {
        "Date": "2024-02-13",
        "bid_price": 98.28125,
        "offer_price": 98.296875,
        "mid_price": 98.2890625,
        "eod_price": 98.0625,
        "bid_yield": 0.3188073318004611,
        "offer_yield": 0.3162490651607517,
        "mid_yield": 0.3175281984806064,
        "eod_yield": 0.354669159650803
    },
    {
        "Date": "2024-02-14",
        "bid_price": 98.3125,
        "offer_price": 98.328125,
        "mid_price": 98.3203125,
        "eod_price": 98.375,
        "bid_yield": 0.3136905380932294,
        "offer_yield": 0.3111335794925693,
        "mid_yield": 0.31241205879289935,
        "eod_yield": 0.30346402004665973
    },
    {
        "Date": "2024-02-15",
        "bid_price": 98.4375,
        "offer_price": 98.453125,
        "mid_price": 98.4453125,
        "eod_price": 98.53125,
        "bid_yield": 0.2932445700168612,
        "offer_yield": 0.2906904938220981,
        "mid_yield": 0.29196753191947966,
        "eod_yield": 0.27792744612693826
    },
    {
        "Date": "2024-02-16",
        "bid_price": 98.0625,
        "offer_price": 98.078125,
        "mid_price": 98.0703125,
        "eod_price": 98.15625,
        "bid_yield": 0.354669159650803,
        "offer_yield": 0.35210584189615046,
        "mid_yield": 0.3533875007734767,
        "eod_yield": 0.33928917908668554
    },
    {
        "Date": "2024-02-20",
        "bid_price": 98.46875,
        "offer_price": 98.484375,
        "mid_price": 98.4765625,
        "eod_price": 98.34375,
        "bid_yield": 0.28813641762733494,
        "offer_yield": 0.28558338904380826,
        "mid_yield": 0.2868599033355716,
        "eod_yield": 0.3085764835061386
    },
    {
        "Date": "2024-02-21",
        "bid_price": 97.96875,
        "offer_price": 97.984375,
        "mid_price": 97.9765625,
        "eod_price": 97.90625,
        "bid_yield": 0.3700659019947055,
        "offer_yield": 0.3674982068538669,
        "mid_yield": 0.36878205442428624,
        "eod_yield": 0.3803387777805331
    },
    {
        "Date": "2024-02-22",
        "bid_price": 97.96875,
        "offer_price": 97.984375,
        "mid_price": 97.9765625,
        "eod_price": 97.90625,
        "bid_yield": 0.3700659019947055,
        "offer_yield": 0.3674982068538669,
        "mid_yield": 0.36878205442428624,
        "eod_yield": 0.3803387777805331
    },
    {
        "Date": "2024-02-23",
        "bid_price": 98.21875,
        "offer_price": 98.21875,
        "mid_price": 98.21875,
        "eod_price": 98.0625,
        "bid_yield": 0.32904477162608153,
        "offer_yield": 0.32904477162608153,
        "mid_yield": 0.32904477162608153,
        "eod_yield": 0.354669159650803
    },
    {
        "Date": "2024-02-26",
        "bid_price": 98.25,
        "offer_price": 98.25,
        "mid_price": 98.25,
        "eod_price": 98.3125,
        "bid_yield": 0.3239249126911167,
        "offer_yield": 0.3239249126911167,
        "mid_yield": 0.3239249126911167,
        "eod_yield": 0.3136905380932294
    },
    {
        "Date": "2024-02-27",
        "bid_price": 98.125,
        "offer_price": 98.140625,
        "mid_price": 98.1328125,
        "eod_price": 98.0,
        "bid_yield": 0.3444140932559971,
        "offer_yield": 0.3418516361713413,
        "mid_yield": 0.3431328647136692,
        "eod_yield": 0.36493143835132785
    },
    {
        "Date": "2024-02-28",
        "bid_price": 98.15625,
        "offer_price": 98.171875,
        "mid_price": 98.1640625,
        "eod_price": 98.125,
        "bid_yield": 0.33928917908668554,
        "offer_yield": 0.33672776961326634,
        "mid_yield": 0.33800847434997594,
        "eod_yield": 0.3444140932559971
    },
    {
        "Date": "2024-02-29",
        "bid_price": 98.125,
        "offer_price": 98.140625,
        "mid_price": 98.1328125,
        "eod_price": 98.28125,
        "bid_yield": 0.3444140932559971,
        "offer_yield": 0.3418516361713413,
        "mid_yield": 0.3431328647136692,
        "eod_yield": 0.3188073318004611
    },
    {
        "Date": "2024-03-01",
        "bid_price": 98.46875,
        "offer_price": 98.484375,
        "mid_price": 98.4765625,
        "eod_price": 98.375,
        "bid_yield": 0.28813641762733494,
        "offer_yield": 0.28558338904380826,
        "mid_yield": 0.2868599033355716,
        "eod_yield": 0.30346402004665973
    },
    {
        "Date": "2024-03-04",
        "bid_price": 98.65625,
        "offer_price": 98.671875,
        "mid_price": 98.6640625,
        "eod_price": 98.8125,
        "bid_yield": 0.25752940773963967,
        "offer_yield": 0.25498161721229584,
        "mid_yield": 0.2562555124759678,
        "eod_yield": 0.2320714070796971
    },
    {
        "Date": "2024-03-05",
        "bid_price": 98.59375,
        "offer_price": 98.609375,
        "mid_price": 98.6015625,
        "eod_price": 98.59375,
        "bid_yield": 0.2677247602939609,
        "offer_yield": 0.26517487454414407,
        "mid_yield": 0.2664498174190525,
        "eod_yield": 0.2677247602939609
    },
    {
        "Date": "2024-03-06",
        "bid_price": 99.0625,
        "offer_price": 99.0625,
        "mid_price": 99.0625,
        "eod_price": 99.125,
        "bid_yield": 0.19142828154563937,
        "offer_yield": 0.19142828154563937,
        "mid_yield": 0.19142828154563937,
        "eod_yield": 0.18128530955314673
    },
    {
        "Date": "2024-03-07",
        "bid_price": 99.34375,
        "offer_price": 99.359375,
        "mid_price": 99.3515625,
        "eod_price": 99.4375,
        "bid_yield": 0.14583833575248759,
        "offer_yield": 0.1433094022274021,
        "mid_yield": 0.14457386898994484,
        "eod_yield": 0.13067206788063085
    },
    {
        "Date": "2024-03-08",
        "bid_price": 99.25,
        "offer_price": 99.265625,
        "mid_price": 99.2578125,
        "eod_price": 99.25,
        "bid_yield": 0.16101927018165627,
        "offer_yield": 0.15848824143409765,
        "mid_yield": 0.15975375580787696,
        "eod_yield": 0.16101927018165627
    },
    {
        "Date": "2024-03-11",
        "bid_price": 99.5,
        "offer_price": 99.5,
        "mid_price": 99.5,
        "eod_price": 99.53125,
        "bid_yield": 0.12056995272636453,
        "offer_yield": 0.12056995272636453,
        "mid_yield": 0.12056995272636453,
        "eod_yield": 0.11552151417732275
    },
    {
        "Date": "2024-03-12",
        "bid_price": 99.46875,
        "offer_price": 99.484375,
        "mid_price": 99.4765625,
        "eod_price": 99.40625,
        "bid_yield": 0.12561981012403894,
        "offer_yield": 0.12309469580650367,
        "mid_yield": 0.12435725296527131,
        "eod_yield": 0.1357257444858555
    },
    {
        "Date": "2024-03-13",
        "bid_price": 99.03125,
        "offer_price": 99.046875,
        "mid_price": 99.0390625,
        "eod_price": 99.0,
        "bid_yield": 0.1965029103755954,
        "offer_yield": 0.19396569748022424,
        "mid_yield": 0.1952343039279098,
        "eod_yield": 0.20157926419305858
    },
    {
        "Date": "2024-03-14",
        "bid_price": 98.90625,
        "offer_price": 98.921875,
        "mid_price": 98.9140625,
        "eod_price": 98.8125,
        "bid_yield": 0.21681713986396825,
        "offer_yield": 0.21427668261528054,
        "mid_yield": 0.21554691123962438,
        "eod_yield": 0.2320714070796971
    },
    {
        "Date": "2024-03-15",
        "bid_price": 98.21875,
        "offer_price": 98.234375,
        "mid_price": 98.2265625,
        "eod_price": 98.1875,
        "bid_yield": 0.32904477162608153,
        "offer_yield": 0.3264852745532993,
        "mid_yield": 0.3277650230896904,
        "eod_yield": 0.33416648973155233
    },
    {
        "Date": "2024-03-18",
        "bid_price": 98.09375,
        "offer_price": 98.09375,
        "mid_price": 98.09375,
        "eod_price": 98.0625,
        "bid_yield": 0.3495411026477817,
        "offer_yield": 0.3495411026477817,
        "mid_yield": 0.3495411026477817,
        "eod_yield": 0.354669159650803
    },
    {
        "Date": "2024-03-19",
        "bid_price": 97.90625,
        "offer_price": 97.921875,
        "mid_price": 97.9140625,
        "eod_price": 97.875,
        "bid_yield": 0.3803387777805331,
        "offer_yield": 0.3777693545638833,
        "mid_yield": 0.37905406617220816,
        "eod_yield": 0.3854773108959202
    },
    {
        "Date": "2024-03-20",
        "bid_price": 98.09375,
        "offer_price": 98.109375,
        "mid_price": 98.1015625,
        "eod_price": 98.125,
        "bid_yield": 0.3495411026477817,
        "offer_yield": 0.3469775979518895,
        "mid_yield": 0.34825935029983557,
        "eod_yield": 0.3444140932559971
    },
    {
        "Date": "2024-03-21",
        "bid_price": 98.21875,
        "offer_price": 98.234375,
        "mid_price": 98.2265625,
        "eod_price": 98.375,
        "bid_yield": 0.32904477162608153,
        "offer_yield": 0.3264852745532993,
        "mid_yield": 0.3277650230896904,
        "eod_yield": 0.30346402004665973
    },
    {
        "Date": "2024-03-22",
        "bid_price": 98.3125,
        "offer_price": 98.328125,
        "mid_price": 98.3203125,
        "eod_price": 98.34375,
        "bid_yield": 0.3136905380932294,
        "offer_yield": 0.3111335794925693,
        "mid_yield": 0.31241205879289935,
        "eod_yield": 0.3085764835061386
    },
    {
        "Date": "2024-03-25",
        "bid_price": 98.5,
        "offer_price": 98.515625,
        "mid_price": 98.5078125,
        "eod_price": 98.5,
        "bid_yield": 0.2830314080715183,
        "offer_yield": 0.2804794270992283,
        "mid_yield": 0.28175541758537326,
        "eod_yield": 0.2830314080715183
    },
    {
        "Date": "2024-03-26",
        "bid_price": 98.75,
        "offer_price": 98.78125,
        "mid_price": 98.765625,
        "eod_price": 98.8125,
        "bid_yield": 0.24224895024299664,
        "offer_yield": 0.2371596548557285,
        "mid_yield": 0.2397043025493626,
        "eod_yield": 0.2320714070796971
    },
    {
        "Date": "2024-03-27",
        "bid_price": 98.71875,
        "offer_price": 98.734375,
        "mid_price": 98.7265625,
        "eod_price": 98.6875,
        "bid_yield": 0.24734138846397435,
        "offer_yield": 0.24479464554786712,
        "mid_yield": 0.24606801700592074,
        "eod_yield": 0.2524338266849521
    },
    {
        "Date": "2024-03-28",
        "bid_price": 98.4375,
        "offer_price": 98.453125,
        "mid_price": 98.4453125,
        "eod_price": 98.59375,
        "bid_yield": 0.2932445700168612,
        "offer_yield": 0.2906904938220981,
        "mid_yield": 0.29196753191947966,
        "eod_yield": 0.2677247602939609
    },
    {
        "Date": "2024-03-29",
        "bid_price": 98.8125,
        "offer_price": 98.8125,
        "mid_price": 98.8125,
        "eod_price": 98.71875,
        "bid_yield": 0.2320714070796971,
        "offer_yield": 0.2320714070796971,
        "mid_yield": 0.2320714070796971,
        "eod_yield": 0.24734138846397435
    },
    {
        "Date": "2024-04-01",
        "bid_price": 0.0,
        "offer_price": 0.0,
        "mid_price": 0.0,
        "eod_price": 98.71875,
        "bid_yield": 954.0007245714852,
        "offer_yield": 954.0007245714852,
        "mid_yield": 954.0007245714852,
        "eod_yield": 0.24734138846397435
    },
    {
        "Date": "2024-04-02",
        "bid_price": 97.71875,
        "offer_price": 97.734375,
        "mid_price": 97.7265625,
        "eod_price": 97.90625,
        "bid_yield": 0.411199309587479,
        "offer_yield": 0.4086255555690543,
        "mid_yield": 0.40991243257826665,
        "eod_yield": 0.3803387777805331
    },
    {
        "Date": "2024-04-03",
        "bid_price": 98.03125,
        "offer_price": 98.046875,
        "mid_price": 98.0390625,
        "eod_price": 98.03125,
        "bid_yield": 0.35979999420050446,
        "offer_yield": 0.35723475956916845,
        "mid_yield": 0.3585173768848364,
        "eod_yield": 0.35979999420050446
    },
    {
        "Date": "2024-04-04",
        "bid_price": 97.8125,
        "offer_price": 97.828125,
        "mid_price": 97.8203125,
        "eod_price": 97.8125,
        "bid_yield": 0.3957612032207321,
        "offer_yield": 0.3931898248195651,
        "mid_yield": 0.3944755140201486,
        "eod_yield": 0.3957612032207321
    },
    {
        "Date": "2024-04-05",
        "bid_price": 97.75,
        "offer_price": 97.765625,
        "mid_price": 97.7578125,
        "eod_price": 97.78125,
        "bid_yield": 0.406051347970963,
        "offer_yield": 0.4034784147739416,
        "mid_yield": 0.40476488137245226,
        "eod_yield": 0.40090548157692
    },
    {
        "Date": "2024-04-08",
        "bid_price": 97.9375,
        "offer_price": 97.953125,
        "mid_price": 97.9453125,
        "eod_price": 98.15625,
        "bid_yield": 0.37520129227638277,
        "offer_yield": 0.37263359713554417,
        "mid_yield": 0.37391744470596344,
        "eod_yield": 0.33928917908668554
    },
    {
        "Date": "2024-04-09",
        "bid_price": 97.375,
        "offer_price": 97.390625,
        "mid_price": 97.3828125,
        "eod_price": 97.46875,
        "bid_yield": 0.46794576708343794,
        "offer_yield": 0.46536081051826506,
        "mid_yield": 0.4666532888008515,
        "eod_yield": 0.45244795441627544
    },
    {
        "Date": "2024-04-10",
        "bid_price": 97.8125,
        "offer_price": 97.828125,
        "mid_price": 97.8203125,
        "eod_price": 97.6875,
        "bid_yield": 0.3957612032207321,
        "offer_yield": 0.3931898248195651,
        "mid_yield": 0.3944755140201486,
        "eod_yield": 0.41634936642646825
    },
    {
        "Date": "2024-04-11",
        "bid_price": 96.40625,
        "offer_price": 96.421875,
        "mid_price": 96.4140625,
        "eod_price": 96.5,
        "bid_yield": 0.6290374488777974,
        "offer_yield": 0.6264254633886329,
        "mid_yield": 0.6277314561332152,
        "eod_yield": 0.6133710337736391
    },
    {
        "Date": "2024-04-12",
        "bid_price": 96.875,
        "offer_price": 96.875,
        "mid_price": 96.875,
        "eod_price": 96.90625,
        "bid_yield": 0.5508720777034762,
        "offer_yield": 0.5508720777034762,
        "mid_yield": 0.5508720777034762,
        "eod_yield": 0.5456759259700779
    },
    {
        "Date": "2024-04-15",
        "bid_price": 96.25,
        "offer_price": 96.265625,
        "mid_price": 96.2578125,
        "eod_price": 96.25,
        "bid_yield": 0.6551837761402134,
        "offer_yield": 0.6525668432712557,
        "mid_yield": 0.6538753097057346,
        "eod_yield": 0.6551837761402134
    },
    {
        "Date": "2024-04-16",
        "bid_price": 96.125,
        "offer_price": 96.140625,
        "mid_price": 96.1328125,
        "eod_price": 96.03125,
        "bid_yield": 0.6761339056491854,
        "offer_yield": 0.6735127823352817,
        "mid_yield": 0.6748233439922335,
        "eod_yield": 0.6918653677298627
    },
    {
        "Date": "2024-04-17",
        "bid_price": 96.3125,
        "offer_price": 96.328125,
        "mid_price": 96.3203125,
        "eod_price": 96.46875,
        "bid_yield": 0.6447202712163761,
        "offer_yield": 0.6421045174787267,
        "mid_yield": 0.6434123943475514,
        "eod_yield": 0.6185912520453982
    },
    {
        "Date": "2024-04-18",
        "bid_price": 96.1875,
        "offer_price": 96.203125,
        "mid_price": 96.1953125,
        "eod_price": 96.125,
        "bid_yield": 0.665654650449753,
        "offer_yield": 0.663036669969559,
        "mid_yield": 0.664345660209656,
        "eod_yield": 0.6761339056491854
    },
    {
        "Date": "2024-04-19",
        "bid_price": 96.28125,
        "offer_price": 96.296875,
        "mid_price": 96.2890625,
        "eod_price": 96.28125,
        "bid_yield": 0.6499508650728681,
        "offer_yield": 0.6473346336993898,
        "mid_yield": 0.648642749386129,
        "eod_yield": 0.6499508650728681
    },
    {
        "Date": "2024-04-22",
        "bid_price": 96.15625,
        "offer_price": 96.171875,
        "mid_price": 96.1640625,
        "eod_price": 96.1875,
        "bid_yield": 0.6708941665952164,
        "offer_yield": 0.6682736785411836,
        "mid_yield": 0.6695839225682,
        "eod_yield": 0.665654650449753
    },
    {
        "Date": "2024-04-23",
        "bid_price": 96.46875,
        "offer_price": 96.484375,
        "mid_price": 96.4765625,
        "eod_price": 96.40625,
        "bid_yield": 0.6185912520453982,
        "offer_yield": 0.6159810123549637,
        "mid_yield": 0.617286132200181,
        "eod_yield": 0.6290374488777974
    },
    {
        "Date": "2024-04-24",
        "bid_price": 96.28125,
        "offer_price": 96.28125,
        "mid_price": 96.28125,
        "eod_price": 96.28125,
        "bid_yield": 0.6499508650728681,
        "offer_yield": 0.6499508650728681,
        "mid_yield": 0.6499508650728681,
        "eod_yield": 0.6499508650728681
    },
    {
        "Date": "2024-04-25",
        "bid_price": 95.84375,
        "offer_price": 95.859375,
        "mid_price": 95.8515625,
        "eod_price": 95.84375,
        "bid_yield": 0.7233790771961217,
        "offer_yield": 0.7207506206035617,
        "mid_yield": 0.7220648488998417,
        "eod_yield": 0.7233790771961217
    },
    {
        "Date": "2024-04-26",
        "bid_price": 96.03125,
        "offer_price": 96.046875,
        "mid_price": 96.0390625,
        "eod_price": 96.0,
        "bid_yield": 0.6918653677298627,
        "offer_yield": 0.6892426650524142,
        "mid_yield": 0.6905540163911384,
        "eod_yield": 0.6971133682727818
    },
    {
        "Date": "2024-04-29",
        "bid_price": 96.28125,
        "offer_price": 96.296875,
        "mid_price": 96.2890625,
        "eod_price": 96.28125,
        "bid_yield": 0.6499508650728681,
        "offer_yield": 0.6473346336993898,
        "mid_yield": 0.648642749386129,
        "eod_yield": 0.6499508650728681
    },
    {
        "Date": "2024-04-30",
        "bid_price": 96.0625,
        "offer_price": 96.078125,
        "mid_price": 96.0703125,
        "eod_price": 95.90625,
        "bid_yield": 0.6866194465160372,
        "offer_yield": 0.6839972755908968,
        "mid_yield": 0.685308361053467,
        "eod_yield": 0.7128673460483554
    },
    {
        "Date": "2024-05-01",
        "bid_price": 96.28125,
        "offer_price": 96.296875,
        "mid_price": 96.2890625,
        "eod_price": 96.28125,
        "bid_yield": 0.6499508650728681,
        "offer_yield": 0.6473346336993898,
        "mid_yield": 0.648642749386129,
        "eod_yield": 0.6499508650728681
    },
    {
        "Date": "2024-05-02",
        "bid_price": 96.0625,
        "offer_price": 96.078125,
        "mid_price": 96.0703125,
        "eod_price": 96.3125,
        "bid_yield": 0.6866194465160372,
        "offer_yield": 0.6839972755908968,
        "mid_yield": 0.685308361053467,
        "eod_yield": 0.6447202712163761
    },
    {
        "Date": "2024-05-03",
        "bid_price": 96.46875,
        "offer_price": 96.484375,
        "mid_price": 96.4765625,
        "eod_price": 96.6875,
        "bid_yield": 0.6185912520453982,
        "offer_yield": 0.6159810123549637,
        "mid_yield": 0.617286132200181,
        "eod_yield": 0.5820889425147221
    },
    {
        "Date": "2024-05-06",
        "bid_price": 97.0625,
        "offer_price": 97.078125,
        "mid_price": 97.0703125,
        "eod_price": 97.15625,
        "bid_yield": 0.5197203099727633,
        "offer_yield": 0.517127472162247,
        "mid_yield": 0.5184238910675052,
        "eod_yield": 0.5041685211658483
    },
    {
        "Date": "2024-05-07",
        "bid_price": 97.5,
        "offer_price": 97.515625,
        "mid_price": 97.5078125,
        "eod_price": 97.3125,
        "bid_yield": 0.44728532624244716,
        "offer_yield": 0.4447050597667696,
        "mid_yield": 0.4459951930046084,
        "eod_yield": 0.47828623795509384
    },
    {
        "Date": "2024-05-08",
        "bid_price": 97.09375,
        "offer_price": 97.109375,
        "mid_price": 97.1015625,
        "eod_price": 97.1875,
        "bid_yield": 0.5145346343517305,
        "offer_yield": 0.5119428441524508,
        "mid_yield": 0.5132387392520907,
        "eod_yield": 0.49898913121223487
    },
    {
        "Date": "2024-05-09",
        "bid_price": 97.1875,
        "offer_price": 97.203125,
        "mid_price": 97.1953125,
        "eod_price": 97.34375,
        "bid_yield": 0.49898913121223487,
        "offer_yield": 0.4963994362354283,
        "mid_yield": 0.4976942837238316,
        "eod_yield": 0.4731141812801364
    },
    {
        "Date": "2024-05-10",
        "bid_price": 97.21875,
        "offer_price": 97.234375,
        "mid_price": 97.2265625,
        "eod_price": 97.125,
        "bid_yield": 0.49381078886985824,
        "offer_yield": 0.49122206033879284,
        "mid_yield": 0.49251642460432554,
        "eod_yield": 0.509351053953171
    },
    {
        "Date": "2024-05-13",
        "bid_price": 97.15625,
        "offer_price": 97.15625,
        "mid_price": 97.15625,
        "eod_price": 97.15625,
        "bid_yield": 0.5041685211658483,
        "offer_yield": 0.5041685211658483,
        "mid_yield": 0.5041685211658483,
        "eod_yield": 0.5041685211658483
    },
    {
        "Date": "2024-05-14",
        "bid_price": 97.28125,
        "offer_price": 97.296875,
        "mid_price": 97.2890625,
        "eod_price": 97.375,
        "bid_yield": 0.4834593422412877,
        "offer_yield": 0.48087174248695413,
        "mid_yield": 0.4821655423641209,
        "eod_yield": 0.46794576708343794
    },
    {
        "Date": "2024-05-15",
        "bid_price": 97.09375,
        "offer_price": 97.109375,
        "mid_price": 97.1015625,
        "eod_price": 97.0625,
        "bid_yield": 0.5145346343517305,
        "offer_yield": 0.5119428441524508,
        "mid_yield": 0.5132387392520907,
        "eod_yield": 0.5197203099727633
    },
    {
        "Date": "2024-05-16",
        "bid_price": 97.90625,
        "offer_price": 97.921875,
        "mid_price": 97.9140625,
        "eod_price": 97.96875,
        "bid_yield": 0.3803387777805331,
        "offer_yield": 0.3777693545638833,
        "mid_yield": 0.37905406617220816,
        "eod_yield": 0.3700659019947055
    },
    {
        "Date": "2024-05-17",
        "bid_price": 97.625,
        "offer_price": 97.640625,
        "mid_price": 97.6328125,
        "eod_price": 97.5,
        "bid_yield": 0.42665471816062966,
        "offer_yield": 0.42407759451866206,
        "mid_yield": 0.42536615633964586,
        "eod_yield": 0.44728532624244716
    },
    {
        "Date": "2024-05-20",
        "bid_price": 97.46875,
        "offer_price": 97.484375,
        "mid_price": 97.4765625,
        "eod_price": 97.4375,
        "bid_yield": 0.45244795441627544,
        "offer_yield": 0.4498666403293614,
        "mid_yield": 0.4511572973728184,
        "eod_yield": 0.45761163020134005
    },
    {
        "Date": "2024-05-21",
        "bid_price": 97.84375,
        "offer_price": 97.859375,
        "mid_price": 97.8515625,
        "eod_price": 97.75,
        "bid_yield": 0.39061898684501684,
        "offer_yield": 0.38804814887046846,
        "mid_yield": 0.38933356785774265,
        "eod_yield": 0.406051347970963
    },
    {
        "Date": "2024-05-22",
        "bid_price": 97.5625,
        "offer_price": 97.578125,
        "mid_price": 97.5703125,
        "eod_price": 97.5625,
        "bid_yield": 0.4369663555622105,
        "offer_yield": 0.4343870336429476,
        "mid_yield": 0.4356766946025791,
        "eod_yield": 0.4369663555622105
    },
    {
        "Date": "2024-05-23",
        "bid_price": 97.0,
        "offer_price": 97.015625,
        "mid_price": 97.0078125,
        "eod_price": 97.125,
        "bid_yield": 0.5300968992710117,
        "offer_yield": 0.5275019662380223,
        "mid_yield": 0.5287994327545169,
        "eod_yield": 0.509351053953171
    },
    {
        "Date": "2024-05-24",
        "bid_price": 97.40625,
        "offer_price": 97.40625,
        "mid_price": 97.40625,
        "eod_price": 97.40625,
        "bid_yield": 0.4627774012088779,
        "offer_yield": 0.4627774012088779,
        "mid_yield": 0.4627774012088779,
        "eod_yield": 0.4627774012088779
    },
    {
        "Date": "2024-05-27",
        "bid_price": 97.125,
        "offer_price": 97.140625,
        "mid_price": 97.1328125,
        "eod_price": 97.15625,
        "bid_yield": 0.509351053953171,
        "offer_yield": 0.5067592637538914,
        "mid_yield": 0.5080551588535311,
        "eod_yield": 0.5041685211658483
    },
    {
        "Date": "2024-05-29",
        "bid_price": 97.0625,
        "offer_price": 97.078125,
        "mid_price": 97.0703125,
        "eod_price": 96.75,
        "bid_yield": 0.5197203099727633,
        "offer_yield": 0.517127472162247,
        "mid_yield": 0.5184238910675052,
        "eod_yield": 0.5716765152529556
    },
    {
        "Date": "2024-05-30",
        "bid_price": 96.40625,
        "offer_price": 96.421875,
        "mid_price": 96.4140625,
        "eod_price": 96.34375,
        "bid_yield": 0.6290374488777974,
        "offer_yield": 0.6264254633886329,
        "mid_yield": 0.6277314561332152,
        "eod_yield": 0.6394896362520441
    },
    {
        "Date": "2024-05-31",
        "bid_price": 96.78125,
        "offer_price": 96.796875,
        "mid_price": 96.7890625,
        "eod_price": 96.71875,
        "bid_yield": 0.5664713452066474,
        "offer_yield": 0.5638714362979279,
        "mid_yield": 0.5651713907522877,
        "eod_yield": 0.5768814838111505
    },
    {
        "Date": "2024-06-03",
        "bid_price": 97.0625,
        "offer_price": 97.0625,
        "mid_price": 97.0625,
        "eod_price": 97.0,
        "bid_yield": 0.5197203099727633,
        "offer_yield": 0.5197203099727633,
        "mid_yield": 0.5197203099727633,
        "eod_yield": 0.5300968992710117
    },
    {
        "Date": "2024-06-04",
        "bid_price": 97.59375,
        "offer_price": 97.609375,
        "mid_price": 97.6015625,
        "eod_price": 97.59375,
        "bid_yield": 0.4318089654445651,
        "offer_yield": 0.4292318418025973,
        "mid_yield": 0.43052040362358124,
        "eod_yield": 0.4318089654445651
    },
    {
        "Date": "2024-06-05",
        "bid_price": 97.96875,
        "offer_price": 97.984375,
        "mid_price": 97.9765625,
        "eod_price": 98.0625,
        "bid_yield": 0.3700659019947055,
        "offer_yield": 0.3674982068538669,
        "mid_yield": 0.36878205442428624,
        "eod_yield": 0.354669159650803
    },
    {
        "Date": "2024-06-06",
        "bid_price": 98.28125,
        "offer_price": 98.296875,
        "mid_price": 98.2890625,
        "eod_price": 98.28125,
        "bid_yield": 0.3188073318004611,
        "offer_yield": 0.3162490651607517,
        "mid_yield": 0.3175281984806064,
        "eod_yield": 0.3188073318004611
    },
    {
        "Date": "2024-06-07",
        "bid_price": 98.3125,
        "offer_price": 98.328125,
        "mid_price": 98.3203125,
        "eod_price": 98.34375,
        "bid_yield": 0.3136905380932294,
        "offer_yield": 0.3111335794925693,
        "mid_yield": 0.31241205879289935,
        "eod_yield": 0.3085764835061386
    },
    {
        "Date": "2024-06-10",
        "bid_price": 97.3125,
        "offer_price": 97.328125,
        "mid_price": 97.3203125,
        "eod_price": 97.28125,
        "bid_yield": 0.47828623795509384,
        "offer_yield": 0.4756996858119967,
        "mid_yield": 0.47699296188354523,
        "eod_yield": 0.4834593422412877
    },
    {
        "Date": "2024-06-11",
        "bid_price": 97.53125,
        "offer_price": 97.546875,
        "mid_price": 97.5390625,
        "eod_price": 97.4375,
        "bid_yield": 0.44212479329109217,
        "offer_yield": 0.43954557442665143,
        "mid_yield": 0.44083518385887177,
        "eod_yield": 0.45761163020134005
    },
    {
        "Date": "2024-06-12",
        "bid_price": 97.40625,
        "offer_price": 97.421875,
        "mid_price": 97.4140625,
        "eod_price": 97.6875,
        "bid_yield": 0.4627774012088779,
        "offer_yield": 0.46019399189949073,
        "mid_yield": 0.4614856965541843,
        "eod_yield": 0.41634936642646825
    },
    {
        "Date": "2024-06-13",
        "bid_price": 98.53125,
        "offer_price": 98.53125,
        "mid_price": 98.53125,
        "eod_price": 98.1875,
        "bid_yield": 0.27792744612693826,
        "offer_yield": 0.27792744612693826,
        "mid_yield": 0.27792744612693826,
        "eod_yield": 0.33416648973155233
    },
    {
        "Date": "2024-06-14",
        "bid_price": 98.53125,
        "offer_price": 98.546875,
        "mid_price": 98.5390625,
        "eod_price": 98.625,
        "bid_yield": 0.27792744612693826,
        "offer_yield": 0.27537651276588476,
        "mid_yield": 0.2766519794464115,
        "eod_yield": 0.2626257984985517
    },
    {
        "Date": "2024-06-17",
        "bid_price": 98.71875,
        "offer_price": 98.75,
        "mid_price": 98.734375,
        "eod_price": 98.75,
        "bid_yield": 0.24734138846397435,
        "offer_yield": 0.24224895024299664,
        "mid_yield": 0.2447951693534855,
        "eod_yield": 0.24224895024299664
    },
    {
        "Date": "2024-06-19",
        "bid_price": 98.34375,
        "offer_price": 98.359375,
        "mid_price": 98.3515625,
        "eod_price": 98.375,
        "bid_yield": 0.3085764835061386,
        "offer_yield": 0.3060201890468601,
        "mid_yield": 0.3072983362764994,
        "eod_yield": 0.30346402004665973
    },
    {
        "Date": "2024-06-20",
        "bid_price": 98.625,
        "offer_price": 98.640625,
        "mid_price": 98.6328125,
        "eod_price": 98.6875,
        "bid_yield": 0.2626257984985517,
        "offer_yield": 0.2600771982669834,
        "mid_yield": 0.26135149838276756,
        "eod_yield": 0.2524338266849521
    },
    {
        "Date": "2024-06-21",
        "bid_price": 98.4375,
        "offer_price": 98.453125,
        "mid_price": 98.4453125,
        "eod_price": 98.53125,
        "bid_yield": 0.2932445700168612,
        "offer_yield": 0.2906904938220981,
        "mid_yield": 0.29196753191947966,
        "eod_yield": 0.27792744612693826
    },
    {
        "Date": "2024-06-24",
        "bid_price": 98.40625,
        "offer_price": 98.421875,
        "mid_price": 98.4140625,
        "eod_price": 98.5,
        "bid_yield": 0.29835377001762425,
        "offer_yield": 0.2957986462116245,
        "mid_yield": 0.2970762081146244,
        "eod_yield": 0.2830314080715183
    },
    {
        "Date": "2024-06-25",
        "bid_price": 98.40625,
        "offer_price": 98.421875,
        "mid_price": 98.4140625,
        "eod_price": 98.5,
        "bid_yield": 0.29835377001762425,
        "offer_yield": 0.2957986462116245,
        "mid_yield": 0.2970762081146244,
        "eod_yield": 0.2830314080715183
    },
    {
        "Date": "2024-06-26",
        "bid_price": 98.46875,
        "offer_price": 98.484375,
        "mid_price": 98.4765625,
        "eod_price": 98.59375,
        "bid_yield": 0.28813641762733494,
        "offer_yield": 0.28558338904380826,
        "mid_yield": 0.2868599033355716,
        "eod_yield": 0.2677247602939609
    },
    {
        "Date": "2024-06-27",
        "bid_price": 98.125,
        "offer_price": 98.140625,
        "mid_price": 98.1328125,
        "eod_price": 98.125,
        "bid_yield": 0.3444140932559971,
        "offer_yield": 0.3418516361713413,
        "mid_yield": 0.3431328647136692,
        "eod_yield": 0.3444140932559971
    },
    {
        "Date": "2024-06-28",
        "bid_price": 98.28125,
        "offer_price": 98.296875,
        "mid_price": 98.2890625,
        "eod_price": 98.3125,
        "bid_yield": 0.3188073318004611,
        "offer_yield": 0.3162490651607517,
        "mid_yield": 0.3175281984806064,
        "eod_yield": 0.3136905380932294
    },
    {
        "Date": "2024-07-01",
        "bid_price": 98.15625,
        "offer_price": 98.171875,
        "mid_price": 98.1640625,
        "eod_price": 98.03125,
        "bid_yield": 0.33928917908668554,
        "offer_yield": 0.33672776961326634,
        "mid_yield": 0.33800847434997594,
        "eod_yield": 0.35979999420050446
    },
    {
        "Date": "2024-07-02",
        "bid_price": 97.65625,
        "offer_price": 97.671875,
        "mid_price": 97.6640625,
        "eod_price": 97.6875,
        "bid_yield": 0.4215010599709348,
        "offer_yield": 0.41892544245719937,
        "mid_yield": 0.42021325121406705,
        "eod_yield": 0.41634936642646825
    },
    {
        "Date": "2024-07-03",
        "bid_price": 97.40625,
        "offer_price": 97.4375,
        "mid_price": 97.421875,
        "eod_price": 97.40625,
        "bid_yield": 0.4627774012088779,
        "offer_yield": 0.45761163020134005,
        "mid_yield": 0.46019451570510894,
        "eod_yield": 0.4627774012088779
    },
    {
        "Date": "2024-07-05",
        "bid_price": 98.65625,
        "offer_price": 98.671875,
        "mid_price": 98.6640625,
        "eod_price": 98.65625,
        "bid_yield": 0.25752940773963967,
        "offer_yield": 0.25498161721229584,
        "mid_yield": 0.2562555124759678,
        "eod_yield": 0.25752940773963967
    },
    {
        "Date": "2024-07-08",
        "bid_price": 98.53125,
        "offer_price": 98.5625,
        "mid_price": 98.546875,
        "eod_price": 98.65625,
        "bid_yield": 0.27792744612693826,
        "offer_yield": 0.2728255794048313,
        "mid_yield": 0.2753765127658848,
        "eod_yield": 0.25752940773963967
    },
    {
        "Date": "2024-07-09",
        "bid_price": 98.34375,
        "offer_price": 98.375,
        "mid_price": 98.359375,
        "eod_price": 98.53125,
        "bid_yield": 0.3085764835061386,
        "offer_yield": 0.30346402004665973,
        "mid_yield": 0.30602025177639913,
        "eod_yield": 0.27792744612693826
    },
    {
        "Date": "2024-07-10",
        "bid_price": 98.5,
        "offer_price": 98.515625,
        "mid_price": 98.5078125,
        "eod_price": 98.59375,
        "bid_yield": 0.2830314080715183,
        "offer_yield": 0.2804794270992283,
        "mid_yield": 0.28175541758537326,
        "eod_yield": 0.2677247602939609
    },
    {
        "Date": "2024-07-11",
        "bid_price": 99.28125,
        "offer_price": 99.296875,
        "mid_price": 99.2890625,
        "eod_price": 99.15625,
        "bid_yield": 0.15595721268653906,
        "offer_yield": 0.1534261839389805,
        "mid_yield": 0.15469169831275978,
        "eod_yield": 0.17621591877937356
    },
    {
        "Date": "2024-07-12",
        "bid_price": 99.15625,
        "offer_price": 99.171875,
        "mid_price": 99.1640625,
        "eod_price": 99.28125,
        "bid_yield": 0.17621591877937356,
        "offer_yield": 0.17368254712510722,
        "mid_yield": 0.1749492329522404,
        "eod_yield": 0.15595721268653906
    },
    {
        "Date": "2024-07-15",
        "bid_price": 99.15625,
        "offer_price": 99.171875,
        "mid_price": 99.1640625,
        "eod_price": 99.0625,
        "bid_yield": 0.17621591877937356,
        "offer_yield": 0.17368254712510722,
        "mid_yield": 0.1749492329522404,
        "eod_yield": 0.19142828154563937
    },
    {
        "Date": "2024-07-16",
        "bid_price": 99.21875,
        "offer_price": 99.234375,
        "mid_price": 99.2265625,
        "eod_price": 99.375,
        "bid_yield": 0.1660834228992466,
        "offer_yield": 0.16355134654045142,
        "mid_yield": 0.16481738471984902,
        "eod_yield": 0.14078046870231667
    },
    {
        "Date": "2024-07-17",
        "bid_price": 99.3125,
        "offer_price": 99.328125,
        "mid_price": 99.3203125,
        "eod_price": 99.46875,
        "bid_yield": 0.15089620280265845,
        "offer_yield": 0.14836726927757302,
        "mid_yield": 0.14963173604011573,
        "eod_yield": 0.12561981012403894
    },
    {
        "Date": "2024-07-18",
        "bid_price": 99.40625,
        "offer_price": 99.421875,
        "mid_price": 99.4140625,
        "eod_price": 99.1875,
        "bid_yield": 0.1357257444858555,
        "offer_yield": 0.1331989061832432,
        "mid_yield": 0.13446232533454935,
        "eod_yield": 0.17114862322807345
    },
    {
        "Date": "2024-07-19",
        "bid_price": 99.0,
        "offer_price": 99.0,
        "mid_price": 99.0,
        "eod_price": 98.9375,
        "bid_yield": 0.20157926419305858,
        "offer_yield": 0.20157926419305858,
        "mid_yield": 0.20157926419305858,
        "eod_yield": 0.21173622536659276
    },
    {
        "Date": "2024-07-22",
        "bid_price": 98.90625,
        "offer_price": 98.921875,
        "mid_price": 98.9140625,
        "eod_price": 98.84375,
        "bid_yield": 0.21681713986396825,
        "offer_yield": 0.21427668261528054,
        "mid_yield": 0.21554691123962438,
        "eod_yield": 0.22698525452613869
    },
    {
        "Date": "2024-07-23",
        "bid_price": 99.03125,
        "offer_price": 99.046875,
        "mid_price": 99.0390625,
        "eod_price": 98.96875,
        "bid_yield": 0.1965029103755954,
        "offer_yield": 0.19396569748022424,
        "mid_yield": 0.1952343039279098,
        "eod_yield": 0.2066563584804539
    },
    {
        "Date": "2024-07-24",
        "bid_price": 99.1875,
        "offer_price": 99.203125,
        "mid_price": 99.1953125,
        "eod_price": 98.875,
        "bid_yield": 0.17114862322807345,
        "offer_yield": 0.16861549925804176,
        "mid_yield": 0.1698820612430576,
        "eod_yield": 0.2219001495838169
    },
    {
        "Date": "2024-07-25",
        "bid_price": 99.4375,
        "offer_price": 99.453125,
        "mid_price": 99.4453125,
        "eod_price": 99.46875,
        "bid_yield": 0.13067206788063085,
        "offer_yield": 0.1281462771892551,
        "mid_yield": 0.12940917253494297,
        "eod_yield": 0.12561981012403894
    },
    {
        "Date": "2024-07-26",
        "bid_price": 99.25,
        "offer_price": 99.265625,
        "mid_price": 99.2578125,
        "eod_price": 99.34375,
        "bid_yield": 0.16101927018165627,
        "offer_yield": 0.15848824143409765,
        "mid_yield": 0.15975375580787696,
        "eod_yield": 0.14583833575248759
    },
    {
        "Date": "2024-07-29",
        "bid_price": 99.125,
        "offer_price": 99.140625,
        "mid_price": 99.1328125,
        "eod_price": 98.90625,
        "bid_yield": 0.18128530955314673,
        "offer_yield": 0.17875009036064185,
        "mid_yield": 0.1800176999568943,
        "eod_yield": 0.21681713986396825
    },
    {
        "Date": "2024-07-30",
        "bid_price": 99.46875,
        "offer_price": 99.484375,
        "mid_price": 99.4765625,
        "eod_price": 99.625,
        "bid_yield": 0.12561981012403894,
        "offer_yield": 0.12309469580650367,
        "mid_yield": 0.12435725296527131,
        "eod_yield": 0.10038667464256322
    },
    {
        "Date": "2024-07-31",
        "bid_price": 99.8125,
        "offer_price": 99.828125,
        "mid_price": 99.8203125,
        "eod_price": 100.0,
        "bid_yield": 0.07016243734125475,
        "offer_yield": 0.0676467282772068,
        "mid_yield": 0.06890458280923079,
        "eod_yield": 0.040000267744064705
    },
    {
        "Date": "2024-08-01",
        "bid_price": 100.53125,
        "offer_price": 100.546875,
        "mid_price": 100.5390625,
        "eod_price": 100.625,
        "bid_yield": -0.045129668951034145,
        "offer_yield": -0.04762612652778587,
        "mid_yield": -0.04637789773941001,
        "eod_yield": -0.06010212874412498
    },
    {
        "Date": "2024-08-02",
        "bid_price": 101.71875,
        "offer_price": 101.734375,
        "mid_price": 101.7265625,
        "eod_price": 101.875,
        "bid_yield": -0.2336745488643642,
        "offer_yield": -0.23613957810401875,
        "mid_yield": -0.2349070634841915,
        "eod_yield": -0.25830598425865126
    },
    {
        "Date": "2024-08-05",
        "bid_price": 101.8125,
        "offer_price": 101.84375,
        "mid_price": 101.828125,
        "eod_price": 101.90625,
        "bid_yield": -0.24845843863487196,
        "offer_yield": -0.25338361779469976,
        "mid_yield": -0.25092102821478585,
        "eod_yield": -0.26322661423683125
    },
    {
        "Date": "2024-08-06",
        "bid_price": 101.375,
        "offer_price": 101.390625,
        "mid_price": 101.3828125,
        "eod_price": 101.21875,
        "bid_yield": -0.1793412396907802,
        "offer_yield": -0.1818156974315639,
        "mid_yield": -0.18057846856117205,
        "eod_yield": -0.1545789077495306
    },
    {
        "Date": "2024-08-07",
        "bid_price": 100.875,
        "offer_price": 100.890625,
        "mid_price": 100.8828125,
        "eod_price": 100.8125,
        "bid_yield": -0.09995535540580709,
        "offer_yield": -0.10244238448142962,
        "mid_yield": -0.10119886994361835,
        "eod_yield": -0.090002001047134
    },
    {
        "Date": "2024-08-08",
        "bid_price": 100.625,
        "offer_price": 100.65625,
        "mid_price": 100.640625,
        "eod_price": 100.59375,
        "bid_yield": -0.06010212874412498,
        "offer_yield": -0.06508980584144554,
        "mid_yield": -0.06259596729278526,
        "eod_yield": -0.055113404035567845
    },
    {
        "Date": "2024-08-09",
        "bid_price": 101.0,
        "offer_price": 101.015625,
        "mid_price": 101.0078125,
        "eod_price": 100.84375,
        "bid_yield": -0.11984111189842182,
        "offer_yield": -0.12232650141023253,
        "mid_yield": -0.12108380665432718,
        "eod_yield": -0.09497920203208883
    },
    {
        "Date": "2024-08-12",
        "bid_price": 101.03125,
        "offer_price": 101.046875,
        "mid_price": 101.0390625,
        "eod_price": 101.125,
        "bid_yield": -0.1248088843822475,
        "offer_yield": -0.12729172301292374,
        "mid_yield": -0.12605030369758563,
        "eod_yield": -0.13970172572135886
    },
    {
        "Date": "2024-08-13",
        "bid_price": 101.40625,
        "offer_price": 101.4375,
        "mid_price": 101.421875,
        "eod_price": 101.5,
        "bid_yield": -0.18428910756111105,
        "offer_yield": -0.1892348802089687,
        "mid_yield": -0.1867619938850399,
        "eod_yield": -0.19912223505973775
    },
    {
        "Date": "2024-08-14",
        "bid_price": 101.65625,
        "offer_price": 101.671875,
        "mid_price": 101.6640625,
        "eod_price": 101.59375,
        "bid_yield": -0.22381024146079972,
        "offer_yield": -0.22627736592292746,
        "mid_yield": -0.2250438036918636,
        "eod_yield": -0.21393964838981586
    },
    {
        "Date": "2024-08-15",
        "bid_price": 100.875,
        "offer_price": 100.890625,
        "mid_price": 100.8828125,
        "eod_price": 100.9375,
        "bid_yield": -0.09995535540580709,
        "offer_yield": -0.10244238448142962,
        "mid_yield": -0.10119886994361835,
        "eod_yield": -0.10990137648582417
    },
    {
        "Date": "2024-08-16",
        "bid_price": 100.875,
        "offer_price": 100.90625,
        "mid_price": 100.890625,
        "eod_price": 101.0625,
        "bid_yield": -0.09995535540580709,
        "offer_yield": -0.10492941355705224,
        "mid_yield": -0.10244238448142967,
        "eod_yield": -0.12977427206512832
    },
    {
        "Date": "2024-08-19",
        "bid_price": 101.15625,
        "offer_price": 101.171875,
        "mid_price": 101.1640625,
        "eod_price": 101.1875,
        "bid_yield": -0.14466216492652856,
        "offer_yield": -0.14714186072349505,
        "mid_yield": -0.1459020128250118,
        "eod_yield": -0.14962099363683393
    },
    {
        "Date": "2024-08-20",
        "bid_price": 101.40625,
        "offer_price": 101.421875,
        "mid_price": 101.4140625,
        "eod_price": 101.46875,
        "bid_yield": -0.18428910756111105,
        "offer_yield": -0.18676233060588465,
        "mid_yield": -0.18552571908349785,
        "eod_yield": -0.19417960524558978
    },
    {
        "Date": "2024-08-21",
        "bid_price": 101.625,
        "offer_price": 101.65625,
        "mid_price": 101.640625,
        "eod_price": 101.6875,
        "bid_yield": -0.2188756225679274,
        "offer_yield": -0.22381024146079972,
        "mid_yield": -0.22134293201436356,
        "eod_yield": -0.2287434427738186
    },
    {
        "Date": "2024-08-22",
        "bid_price": 101.25,
        "offer_price": 101.265625,
        "mid_price": 101.2578125,
        "eod_price": 101.28125,
        "bid_yield": -0.15953510165214502,
        "offer_yield": -0.16201165461540182,
        "mid_yield": -0.1607733781337734,
        "eod_yield": -0.16448924390407843
    },
    {
        "Date": "2024-08-23",
        "bid_price": 101.625,
        "offer_price": 101.640625,
        "mid_price": 101.6328125,
        "eod_price": 101.65625,
        "bid_yield": -0.2188756225679274,
        "offer_yield": -0.22134311699867215,
        "mid_yield": -0.22010936978329976,
        "eod_yield": -0.22381024146079972
    },
    {
        "Date": "2024-08-26",
        "bid_price": 101.46875,
        "offer_price": 101.484375,
        "mid_price": 101.4765625,
        "eod_price": 101.5,
        "bid_yield": -0.19417960524558978,
        "offer_yield": -0.19665092015266372,
        "mid_yield": -0.19541526269912673,
        "eod_yield": -0.19912223505973775
    },
    {
        "Date": "2024-08-27",
        "bid_price": 101.65625,
        "offer_price": 101.671875,
        "mid_price": 101.6640625,
        "eod_price": 101.5625,
        "bid_yield": -0.22381024146079972,
        "offer_yield": -0.22627736592292746,
        "mid_yield": -0.2250438036918636,
        "eod_yield": -0.20900225663185076
    },
    {
        "Date": "2024-08-28",
        "bid_price": 101.625,
        "offer_price": 101.640625,
        "mid_price": 101.6328125,
        "eod_price": 101.5,
        "bid_yield": -0.2188756225679274,
        "offer_yield": -0.22134311699867215,
        "mid_yield": -0.22010936978329976,
        "eod_yield": -0.19912223505973775
    },
    {
        "Date": "2024-08-29",
        "bid_price": 101.28125,
        "offer_price": 101.296875,
        "mid_price": 101.2890625,
        "eod_price": 101.34375,
        "bid_yield": -0.16448924390407843,
        "offer_yield": -0.16696580815315204,
        "mid_yield": -0.16572752602861524,
        "eod_yield": -0.17439232420921286
    },
    {
        "Date": "2024-08-30",
        "bid_price": 101.34375,
        "offer_price": 101.34375,
        "mid_price": 101.34375,
        "eod_price": 101.125,
        "bid_yield": -0.17439232420921286,
        "offer_yield": -0.17439232420921286,
        "mid_yield": -0.17439232420921286,
        "eod_yield": -0.13970172572135886
    },
    {
        "Date": "2024-09-03",
        "bid_price": 101.46875,
        "offer_price": 101.484375,
        "mid_price": 101.4765625,
        "eod_price": 101.53125,
        "bid_yield": -0.19417960524558978,
        "offer_yield": -0.19665092015266372,
        "mid_yield": -0.19541526269912673,
        "eod_yield": -0.20406235650614157
    },
    {
        "Date": "2024-09-04",
        "bid_price": 101.84375,
        "offer_price": 101.859375,
        "mid_price": 101.8515625,
        "eod_price": 102.03125,
        "bid_yield": -0.25338361779469976,
        "offer_yield": -0.2558440978527065,
        "mid_yield": -0.25461385782370316,
        "eod_yield": -0.282896562814712
    },
    {
        "Date": "2024-09-05",
        "bid_price": 102.03125,
        "offer_price": 102.046875,
        "mid_price": 102.0390625,
        "eod_price": 102.15625,
        "bid_yield": -0.282896562814712,
        "offer_yield": -0.2853532111644741,
        "mid_yield": -0.28412488698959304,
        "eod_yield": -0.3025392735004421
    },
    {
        "Date": "2024-09-06",
        "bid_price": 102.5625,
        "offer_price": 102.578125,
        "mid_price": 102.5703125,
        "eod_price": 102.34375,
        "bid_yield": -0.3662008705871117,
        "offer_yield": -0.368643542528152,
        "mid_yield": -0.36742220655763186,
        "eod_yield": -0.33195514941215476
    },
    {
        "Date": "2024-09-09",
        "bid_price": 102.375,
        "offer_price": 102.390625,
        "mid_price": 102.3828125,
        "eod_price": 102.4375,
        "bid_yield": -0.33685168433189355,
        "offer_yield": -0.3392999517917628,
        "mid_yield": -0.3380758180618282,
        "eod_yield": -0.34664032791463406
    },
    {
        "Date": "2024-09-10",
        "bid_price": 102.59375,
        "offer_price": 102.640625,
        "mid_price": 102.6171875,
        "eod_price": 102.75,
        "bid_yield": -0.371085524320602,
        "offer_yield": -0.3784114696979518,
        "mid_yield": -0.3747484970092769,
        "eod_yield": -0.39548962807655286
    },
    {
        "Date": "2024-09-11",
        "bid_price": 102.46875,
        "offer_price": 102.484375,
        "mid_price": 102.4765625,
        "eod_price": 102.53125,
        "bid_yield": -0.3515326556835739,
        "offer_yield": -0.35397854370972626,
        "mid_yield": -0.35275559969665005,
        "eod_yield": -0.3613123590946193
    },
    {
        "Date": "2024-09-12",
        "bid_price": 102.8125,
        "offer_price": 102.828125,
        "mid_price": 102.8203125,
        "eod_price": 102.6875,
        "bid_yield": -0.40524079346656755,
        "offer_yield": -0.4076775372028345,
        "mid_yield": -0.40645916533470106,
        "eod_yield": -0.3857332246303554
    },
    {
        "Date": "2024-09-13",
        "bid_price": 102.71875,
        "offer_price": 102.734375,
        "mid_price": 102.7265625,
        "eod_price": 102.75,
        "bid_yield": -0.39061195015907246,
        "offer_yield": -0.39305183672904925,
        "mid_yield": -0.3918318934440609,
        "eod_yield": -0.39548962807655286
    },
    {
        "Date": "2024-09-16",
        "bid_price": 102.875,
        "offer_price": 102.890625,
        "mid_price": 102.8828125,
        "eod_price": 102.875,
        "bid_yield": -0.41498462557792626,
        "offer_yield": -0.4174192076333784,
        "mid_yield": -0.4162019166056523,
        "eod_yield": -0.41498462557792626
    },
    {
        "Date": "2024-09-17",
        "bid_price": 102.65625,
        "offer_price": 102.671875,
        "mid_price": 102.6640625,
        "eod_price": 102.71875,
        "bid_yield": -0.3808526164981686,
        "offer_yield": -0.3832933380603786,
        "mid_yield": -0.3820729772792736,
        "eod_yield": -0.39061195015907246
    },
    {
        "Date": "2024-09-18",
        "bid_price": 102.4375,
        "offer_price": 102.453125,
        "mid_price": 102.4453125,
        "eod_price": 102.46875,
        "bid_yield": -0.34664032791463406,
        "offer_yield": -0.3490877835750576,
        "mid_yield": -0.3478640557448458,
        "eod_yield": -0.3515326556835739
    },
    {
        "Date": "2024-09-19",
        "bid_price": 102.28125,
        "offer_price": 102.296875,
        "mid_price": 102.2890625,
        "eod_price": 102.3125,
        "bid_yield": -0.3221557939052577,
        "offer_yield": -0.3246061565876002,
        "mid_yield": -0.32338097524642895,
        "eod_yield": -0.3270565192699428
    },
    {
        "Date": "2024-09-20",
        "bid_price": 102.125,
        "offer_price": 102.140625,
        "mid_price": 102.1328125,
        "eod_price": 102.375,
        "bid_yield": -0.29763121485710103,
        "offer_yield": -0.3000847203731532,
        "mid_yield": -0.2988579676151271,
        "eod_yield": -0.33685168433189355
    },
    {
        "Date": "2024-09-23",
        "bid_price": 102.0625,
        "offer_price": 102.078125,
        "mid_price": 102.0703125,
        "eod_price": 102.21875,
        "bid_yield": -0.28780952487741623,
        "offer_yield": -0.2902654602527614,
        "mid_yield": -0.2890374925650888,
        "eod_yield": -0.3123516156270192
    },
    {
        "Date": "2024-09-24",
        "bid_price": 102.3125,
        "offer_price": 102.328125,
        "mid_price": 102.3203125,
        "eod_price": 102.375,
        "bid_yield": -0.3270565192699428,
        "offer_yield": -0.3295069185369816,
        "mid_yield": -0.3282817189034622,
        "eod_yield": -0.33685168433189355
    },
    {
        "Date": "2024-09-25",
        "bid_price": 102.09375,
        "offer_price": 102.109375,
        "mid_price": 102.1015625,
        "eod_price": 102.09375,
        "bid_yield": -0.2927210609912868,
        "offer_yield": -0.2951766961110021,
        "mid_yield": -0.2939488785511445,
        "eod_yield": -0.2927210609912868
    },
    {
        "Date": "2024-09-26",
        "bid_price": 101.9375,
        "offer_price": 101.96875,
        "mid_price": 101.953125,
        "eod_price": 102.0,
        "bid_yield": -0.2681472442150111,
        "offer_yield": -0.2730647313594813,
        "mid_yield": -0.2706059877872462,
        "eod_yield": -0.2779819933905404
    },
    {
        "Date": "2024-09-27",
        "bid_price": 102.15625,
        "offer_price": 102.171875,
        "mid_price": 102.1640625,
        "eod_price": 102.28125,
        "bid_yield": -0.3025392735004421,
        "offer_yield": -0.30499277901649435,
        "mid_yield": -0.3037660262584682,
        "eod_yield": -0.3221557939052577
    },
    {
        "Date": "2024-09-30",
        "bid_price": 102.0625,
        "offer_price": 102.078125,
        "mid_price": 102.0703125,
        "eod_price": 101.875,
        "bid_yield": -0.28780952487741623,
        "offer_yield": -0.2902654602527614,
        "mid_yield": -0.2890374925650888,
        "eod_yield": -0.25830598425865126
    },
    {
        "Date": "2024-10-01",
        "bid_price": 100.125,
        "offer_price": 100.140625,
        "mid_price": 100.1328125,
        "eod_price": 100.125,
        "bid_yield": 0.01992594122886696,
        "offer_yield": 0.017417959928512954,
        "mid_yield": 0.018671950578689957,
        "eod_yield": 0.01992594122886696
    },
    {
        "Date": "2024-10-02",
        "bid_price": 101.96875,
        "offer_price": 101.984375,
        "mid_price": 101.9765625,
        "eod_price": 102.0625,
        "bid_yield": -0.2730647313594813,
        "offer_yield": -0.2755234749317164,
        "mid_yield": -0.2742941031455989,
        "eod_yield": -0.28780952487741623
    },
    {
        "Date": "2024-10-03",
        "bid_price": 101.8125,
        "offer_price": 101.828125,
        "mid_price": 101.8203125,
        "eod_price": 101.65625,
        "bid_yield": -0.24845843863487196,
        "offer_yield": -0.25092032504081685,
        "mid_yield": -0.2496893818378444,
        "eod_yield": -0.22381024146079972
    },
    {
        "Date": "2024-10-04",
        "bid_price": 100.8125,
        "offer_price": 100.828125,
        "mid_price": 100.8203125,
        "eod_price": 100.6875,
        "bid_yield": -0.090002001047134,
        "offer_yield": -0.0924911253452297,
        "mid_yield": -0.09124656319618185,
        "eod_yield": -0.07007538771629294
    },
    {
        "Date": "2024-10-07",
        "bid_price": 100.4375,
        "offer_price": 100.453125,
        "mid_price": 100.4453125,
        "eod_price": 100.375,
        "bid_yield": -0.03014255401358727,
        "offer_yield": -0.03264109539985618,
        "mid_yield": -0.03139182470672172,
        "eod_yield": -0.02014204573631248
    },
    {
        "Date": "2024-10-08",
        "bid_price": 100.4375,
        "offer_price": 100.46875,
        "mid_price": 100.453125,
        "eod_price": 100.40625,
        "bid_yield": -0.03014255401358727,
        "offer_yield": -0.03513964819908103,
        "mid_yield": -0.03264110110633415,
        "eod_yield": -0.025143341779708474
    },
    {
        "Date": "2024-10-09",
        "bid_price": 100.1875,
        "offer_price": 100.203125,
        "mid_price": 100.1953125,
        "eod_price": 100.09375,
        "bid_yield": 0.009898206472397234,
        "offer_yield": 0.0073923616026281575,
        "mid_yield": 0.008645284037512696,
        "eod_yield": 0.024941903829574962
    },
    {
        "Date": "2024-10-10",
        "bid_price": 100.28125,
        "offer_price": 100.296875,
        "mid_price": 100.2890625,
        "eod_price": 100.1875,
        "bid_yield": -0.005129776716231914,
        "offer_yield": -0.007633249804913469,
        "mid_yield": -0.006381513260572692,
        "eod_yield": 0.009898206472397234
    },
    {
        "Date": "2024-10-11",
        "bid_price": 100.21875,
        "offer_price": 100.234375,
        "mid_price": 100.2265625,
        "eod_price": 100.21875,
        "bid_yield": 0.004887481927872089,
        "offer_yield": 0.0023826434612278027,
        "mid_yield": 0.003635062694549946,
        "eod_yield": 0.004887481927872089
    },
    {
        "Date": "2024-10-15",
        "bid_price": 100.59375,
        "offer_price": 100.609375,
        "mid_price": 100.6015625,
        "eod_price": 100.46875,
        "bid_yield": -0.055113404035567845,
        "offer_yield": -0.05760776638984641,
        "mid_yield": -0.05636058521270713,
        "eod_yield": -0.03513964819908103
    },
    {
        "Date": "2024-10-16",
        "bid_price": 100.34375,
        "offer_price": 100.359375,
        "mid_price": 100.3515625,
        "eod_price": 100.40625,
        "bid_yield": -0.015139702081679907,
        "offer_yield": -0.017641397714614475,
        "mid_yield": -0.016390549898147193,
        "eod_yield": -0.025143341779708474
    },
    {
        "Date": "2024-10-17",
        "bid_price": 100.25,
        "offer_price": 100.265625,
        "mid_price": 100.2578125,
        "eod_price": 100.25,
        "bid_yield": -0.00012219500541648447,
        "offer_yield": -0.002625985860824199,
        "mid_yield": -0.0013740904331203418,
        "eod_yield": -0.00012219500541648447
    },
    {
        "Date": "2024-10-18",
        "bid_price": 102.34375,
        "offer_price": 102.375,
        "mid_price": 102.359375,
        "eod_price": 102.25,
        "bid_yield": -0.33195514941215476,
        "offer_yield": -0.33685168433189355,
        "mid_yield": -0.33440341687202413,
        "eod_yield": -0.3172540209293361
    },
    {
        "Date": "2024-10-21",
        "bid_price": 99.53125,
        "offer_price": 99.546875,
        "mid_price": 99.5390625,
        "eod_price": 99.53125,
        "bid_yield": 0.11552151417732275,
        "offer_yield": 0.11299781870842017,
        "mid_yield": 0.11425966644287146,
        "eod_yield": 0.11552151417732275
    },
    {
        "Date": "2024-10-22",
        "bid_price": 99.75,
        "offer_price": 99.78125,
        "mid_price": 99.765625,
        "eod_price": 99.6875,
        "bid_yield": 0.08023063445091284,
        "offer_yield": 0.07519581484794653,
        "mid_yield": 0.07771322464942969,
        "eod_yield": 0.09030427363697859
    },
    {
        "Date": "2024-10-23",
        "bid_price": 99.34375,
        "offer_price": 99.359375,
        "mid_price": 99.3515625,
        "eod_price": 99.3125,
        "bid_yield": 0.14583833575248759,
        "offer_yield": 0.1433094022274021,
        "mid_yield": 0.14457386898994484,
        "eod_yield": 0.15089620280265845
    },
    {
        "Date": "2024-10-24",
        "bid_price": 99.53125,
        "offer_price": 99.546875,
        "mid_price": 99.5390625,
        "eod_price": 99.4375,
        "bid_yield": 0.11552151417732275,
        "offer_yield": 0.11299781870842017,
        "mid_yield": 0.11425966644287146,
        "eod_yield": 0.13067206788063085
    },
    {
        "Date": "2024-10-25",
        "bid_price": 99.5,
        "offer_price": 99.515625,
        "mid_price": 99.5078125,
        "eod_price": 99.21875,
        "bid_yield": 0.12056995272636453,
        "offer_yield": 0.11804520964622534,
        "mid_yield": 0.11930758118629493,
        "eod_yield": 0.1660834228992466
    },
    {
        "Date": "2024-10-28",
        "bid_price": 99.09375,
        "offer_price": 99.125,
        "mid_price": 99.109375,
        "eod_price": 99.03125,
        "bid_yield": 0.18635574793815649,
        "offer_yield": 0.18128530955314673,
        "mid_yield": 0.1838205287456516,
        "eod_yield": 0.1965029103755954
    },
    {
        "Date": "2024-10-29",
        "bid_price": 98.75,
        "offer_price": 98.765625,
        "mid_price": 98.7578125,
        "eod_price": 99.0625,
        "bid_yield": 0.24224895024299664,
        "offer_yield": 0.23970430254936265,
        "mid_yield": 0.24097662639617964,
        "eod_yield": 0.19142828154563937
    },
    {
        "Date": "2024-10-30",
        "bid_price": 99.0,
        "offer_price": 99.015625,
        "mid_price": 99.0078125,
        "eod_price": 98.90625,
        "bid_yield": 0.20157926419305858,
        "offer_yield": 0.19903982406721718,
        "mid_yield": 0.20030954413013788,
        "eod_yield": 0.21681713986396825
    },
    {
        "Date": "2024-10-31",
        "bid_price": 98.6875,
        "offer_price": 98.703125,
        "mid_price": 98.6953125,
        "eod_price": 98.4375,
        "bid_yield": 0.2524338266849521,
        "offer_yield": 0.24988740708902657,
        "mid_yield": 0.2511606168869893,
        "eod_yield": 0.2932445700168612
    },
    {
        "Date": "2024-11-01",
        "bid_price": 98.6875,
        "offer_price": 98.703125,
        "mid_price": 98.6953125,
        "eod_price": 98.875,
        "bid_yield": 0.2524338266849521,
        "offer_yield": 0.24988740708902657,
        "mid_yield": 0.2511606168869893,
        "eod_yield": 0.2219001495838169
    },
    {
        "Date": "2024-11-04",
        "bid_price": 98.8125,
        "offer_price": 98.828125,
        "mid_price": 98.8203125,
        "eod_price": 98.71875,
        "bid_yield": 0.2320714070796971,
        "offer_yield": 0.22952780699729952,
        "mid_yield": 0.2307996070384983,
        "eod_yield": 0.24734138846397435
    },
    {
        "Date": "2024-11-05",
        "bid_price": 98.40625,
        "offer_price": 98.421875,
        "mid_price": 98.4140625,
        "eod_price": 98.8125,
        "bid_yield": 0.29835377001762425,
        "offer_yield": 0.2957986462116245,
        "mid_yield": 0.2970762081146244,
        "eod_yield": 0.2320714070796971
    }
]